atmose/__init__.py
atmose/clustering.py
atmose/labeling.py
atmose/plotting.py
atmose-0.0.38.dist-info/LICENSE
atmose-0.0.38.dist-info/METADATA
atmose-0.0.38.dist-info/WHEEL
atmose-0.0.38.dist-info/RECORD
