Metadata-Version: 2.1
Name: atmose
Version: 0.0.38
Summary: ATMOSE- Automatic Topic Modeling Over Semantic Embeddings
License: MIT
Author: Joe Nance
Author-email: joe@nceno.app
Requires-Python: >=3.10,<4.0
Classifier: License :: OSI Approved :: MIT License
Classifier: Programming Language :: Python :: 3
Classifier: Programming Language :: Python :: 3.10
Classifier: Programming Language :: Python :: 3.11
Classifier: Programming Language :: Python :: 3.12
Requires-Dist: asyncio (>=3.4.3,<4.0.0)
Requires-Dist: backoff (>=2.2.1,<3.0.0)
Requires-Dist: hdbscan (>=0.8.40,<0.9.0)
Requires-Dist: httpx (>=0.28.1,<0.29.0)
Requires-Dist: llvmlite (>=0.44.0,<0.45.0)
Requires-Dist: openai (>=1.59.9,<2.0.0)
Requires-Dist: optuna (>=4.2.0,<5.0.0)
Requires-Dist: pandas (>=2.2.2,<3.0.0)
Requires-Dist: plotly (>=5.24.1,<6.0.0)
Requires-Dist: psutil (>=6.1.1,<7.0.0)
Requires-Dist: python-dotenv (>=1.0.1,<2.0.0)
Requires-Dist: scikit-learn (>=1.6.1,<2.0.0)
Requires-Dist: tqdm (>=4.67.1,<5.0.0)
Requires-Dist: umap-learn (>=0.5.7,<0.6.0)
